easyreq/__init__.py
easyreq/config.py
easyreq/main.py
easyreq-1.2.0.dist-info/LICENSE.txt
easyreq-1.2.0.dist-info/METADATA
easyreq-1.2.0.dist-info/WHEEL
easyreq-1.2.0.dist-info/entry_points.txt
easyreq-1.2.0.dist-info/top_level.txt
easyreq-1.2.0.dist-info/RECORD
