Metadata-Version: 2.1
Name: easyreq
Version: 1.2.0
Summary: Test package
Home-page: https://kjaniszewski.pl
Author: Krzysztof Janiszewski
Author-email: krzychu.janiszewski@gmail.com
License: MIT
Download-URL: https://gitlab.com/Krzysidlo/easyreq
Platform: UNKNOWN
Classifier: Programming Language :: Python :: 3
Classifier: License :: OSI Approved :: MIT License
Classifier: Operating System :: OS Independent
Requires-Python: >=3
Requires-Dist: argparse (>=1.1)
